{
    "1024": {
        "N": 1024,
        "avg_time_ref": 0.1675886803865433,
        "tflops_ref": 820.0968773964748,
        "avg_time": 0.15151650056242943,
        "tflops": 907.0890164558081,
        "max_error": 0.001953125,
        "mean_error": 0.00010652463970473036,
        "error_count": 0
    },
    "2048": {
        "N": 2048,
        "avg_time_ref": 0.51134202003479,
        "tflops_ref": 1075.123483594398,
        "avg_time": 0.511869820356369,
        "tflops": 1074.014899931499,
        "max_error": 0.001953125,
        "mean_error": 7.708072371315211e-05,
        "error_count": 0
    },
    "4096": {
        "N": 4096,
        "avg_time_ref": 1.836383776664734,
        "tflops_ref": 1197.474778145719,
        "avg_time": 1.9463440907001495,
        "tflops": 1129.8224533160296,
        "max_error": 0.001953125,
        "mean_error": 5.5451830121455714e-05,
        "error_count": 0
    },
    "8192": {
        "N": 8192,
        "avg_time_ref": 7.002260575294494,
        "tflops_ref": 1256.1790478409985,
        "avg_time": 7.32407922744751,
        "tflops": 1200.982778728555,
        "max_error": 0.0009765625,
        "mean_error": 3.973543789470568e-05,
        "error_count": 0
    },
    "16384": {
        "N": 16384,
        "avg_time_ref": 25.765799160003663,
        "tflops_ref": 1280.198942343821,
        "avg_time": 27.031943912506105,
        "tflops": 1220.2359157019264,
        "max_error": 0.000732421875,
        "mean_error": 2.8378990464261733e-05,
        "error_count": 0
    }
}